{
  "model_id": "3d958b87-f331-48e2-8558-ad99c25dd029",
  "model_name": "Model_CONSUMER",
  "created_at": "2025-12-16T17:43:04.240900",
  "created_by": "system",
  "segment": "CONSUMER",
  "data_info": {
    "train_records": 5600,
    "test_records": 2400,
    "train_bad_rate": 0.12607142329216003,
    "test_bad_rate": 0.1262499988079071,
    "feature_names": [
      "payment_history",
      "credit_utilization",
      "account_tenure",
      "monthly_income",
      "recent_inquiries",
      "num_credit_lines"
    ]
  },
  "architecture": {
    "input_dim": 6,
    "hidden_layers": [
      64,
      32
    ],
    "activation_function": "relu",
    "dropout_rate": 0.2,
    "use_batch_normalization": true
  },
  "regularization": {
    "l1_lambda": 0.0,
    "l2_lambda": 0.01,
    "gradient_clip_norm": 1.0
  },
  "loss_function": {
    "loss_type": "combined",
    "loss_alpha": 0.3,
    "auc_gamma": 2.0
  },
  "optimizer": {
    "optimizer_type": "adam",
    "learning_rate": 0.001,
    "weight_decay": 0.01
  },
  "training": {
    "batch_size": 256,
    "epochs": 100,
    "early_stopping": {
      "enabled": false,
      "patience": 10,
      "min_delta": 0.001,
      "monitor": "test_ar"
    }
  },
  "final_metrics": {
    "discrimination": {
      "auc_roc": 0.5990366561691935,
      "gini_ar": 0.1980733123383871,
      "ks_statistic": 0.18902060389518738
    }
  },
  "training_history": {
    "epochs": [
      {
        "epoch": 1,
        "train_loss": 0.7934552864594893,
        "test_loss": 0.743264764547348,
        "train_bce_loss": 1.0203232006593184,
        "train_auc_loss": 0.696226179599762,
        "test_bce_loss": 0.8735241770744324,
        "test_auc_loss": 0.6874392628669739,
        "train_auc": 0.5781533090759222,
        "test_auc": 0.5537007921106846,
        "train_ar": 0.15630661815184443,
        "test_ar": 0.10740158422136914,
        "train_ks": 0.12156179547309875,
        "test_ks": 0.11214041709899902,
        "learning_rate": 0.001,
        "epoch_time_seconds": 0.1493821144104004
      },
      {
        "epoch": 2,
        "train_loss": 0.7241491296074607,
        "test_loss": 0.6918551504611969,
        "train_bce_loss": 0.8136625262823972,
        "train_auc_loss": 0.6857862418348138,
        "test_bce_loss": 0.7149914026260376,
        "test_auc_loss": 0.6819396018981934,
        "train_auc": 0.6034519634957993,
        "test_auc": 0.5747523965558216,
        "train_ar": 0.20690392699159865,
        "test_ar": 0.1495047931116431,
        "train_ks": 0.1657843291759491,
        "test_ks": 0.1468670666217804,
        "learning_rate": 0.001,
        "epoch_time_seconds": 0.1383829116821289
      },
      {
        "epoch": 3,
        "train_loss": 0.6774763519113715,
        "test_loss": 0.6569583773612976,
        "train_bce_loss": 0.6740230917930603,
        "train_auc_loss": 0.6789563244039362,
        "test_bce_loss": 0.6037815749645233,
        "test_auc_loss": 0.6797484278678894,
        "train_auc": 0.6127211327740159,
        "test_auc": 0.5832274929925039,
        "train_ar": 0.2254422655480317,
        "test_ar": 0.16645498598500774,
        "train_ks": 0.17823699116706848,
        "test_ks": 0.16782104969024658,
        "learning_rate": 0.001,
        "epoch_time_seconds": 0.22685003280639648
      },
      {
        "epoch": 4,
        "train_loss": 0.6467399190772664,
        "test_loss": 0.6330349862575531,
        "train_bce_loss": 0.5788084458221089,
        "train_auc_loss": 0.6758534095504067,
        "test_bce_loss": 0.5243520081043244,
        "test_auc_loss": 0.6796134173870086,
        "train_auc": 0.6178171282173581,
        "test_auc": 0.585643328281326,
        "train_ar": 0.23563425643471625,
        "test_ar": 0.17128665656265207,
        "train_ks": 0.1803474724292755,
        "test_ks": 0.1753896176815033,
        "learning_rate": 0.001,
        "epoch_time_seconds": 0.1429760456085205
      },
      {
        "epoch": 5,
        "train_loss": 0.6219940700314261,
        "test_loss": 0.6214581251144409,
        "train_bce_loss": 0.5101974525234916,
        "train_auc_loss": 0.6699069196527655,
        "test_bce_loss": 0.4849188983440399,
        "test_auc_loss": 0.6799749374389649,
        "train_auc": 0.6224170545884364,
        "test_auc": 0.5842331729596422,
        "train_ar": 0.24483410917687287,
        "test_ar": 0.16846634591928433,
        "train_ks": 0.18445029854774475,
        "test_ks": 0.17216485738754272,
        "learning_rate": 0.001,
        "epoch_time_seconds": 0.14376211166381836
      },
      {
        "epoch": 6,
        "train_loss": 0.6158046505667947,
        "test_loss": 0.6114088118076324,
        "train_bce_loss": 0.47657510638237,
        "train_auc_loss": 0.6754744513468309,
        "test_bce_loss": 0.4510244756937027,
        "test_auc_loss": 0.6801449596881867,
        "train_auc": 0.6266436267569354,
        "test_auc": 0.5852530174333599,
        "train_ar": 0.2532872535138708,
        "test_ar": 0.17050603486671978,
        "train_ks": 0.19655275344848633,
        "test_ks": 0.1841244399547577,
        "learning_rate": 0.001,
        "epoch_time_seconds": 0.15532803535461426
      },
      {
        "epoch": 7,
        "train_loss": 0.6035859937017615,
        "test_loss": 0.6046101093292237,
        "train_bce_loss": 0.4473409774628552,
        "train_auc_loss": 0.670548143711957,
        "test_bce_loss": 0.42844859659671786,
        "test_auc_loss": 0.6801078975200653,
        "train_auc": 0.6304558915293167,
        "test_auc": 0.5884101285665048,
        "train_ar": 0.2609117830586334,
        "test_ar": 0.17682025713300953,
        "train_ks": 0.19301775097846985,
        "test_ks": 0.1846013069152832,
        "learning_rate": 0.001,
        "epoch_time_seconds": 0.14838695526123047
      },
      {
        "epoch": 8,
        "train_loss": 0.5977555946870283,
        "test_loss": 0.6004298090934753,
        "train_bce_loss": 0.4239792214198546,
        "train_auc_loss": 0.6722311783920635,
        "test_bce_loss": 0.41606571674346926,
        "test_auc_loss": 0.6794430017471313,
        "train_auc": 0.6340403812959385,
        "test_auc": 0.5913563459350227,
        "train_ar": 0.2680807625918771,
        "test_ar": 0.18271269187004546,
        "train_ks": 0.20649385452270508,
        "test_ks": 0.17881745100021362,
        "learning_rate": 0.001,
        "epoch_time_seconds": 0.1470327377319336
      },
      {
        "epoch": 9,
        "train_loss": 0.5967923321507194,
        "test_loss": 0.5982953429222106,
        "train_bce_loss": 0.4177461970936168,
        "train_auc_loss": 0.6735263819044287,
        "test_bce_loss": 0.41028204560279846,
        "test_auc_loss": 0.6788724720478058,
        "train_auc": 0.6364969940645364,
        "test_auc": 0.5929899856938484,
        "train_ar": 0.27299398812907283,
        "test_ar": 0.18597997138769684,
        "train_ks": 0.21311986446380615,
        "test_ks": 0.18274575471878052,
        "learning_rate": 0.001,
        "epoch_time_seconds": 0.6644349098205566
      },
      {
        "epoch": 10,
        "train_loss": 0.5954044515436346,
        "test_loss": 0.5959288895130157,
        "train_bce_loss": 0.41542724587700586,
        "train_auc_loss": 0.672537540847605,
        "test_bce_loss": 0.40240896344184873,
        "test_auc_loss": 0.6788660109043121,
        "train_auc": 0.6391504136996102,
        "test_auc": 0.5931914364540889,
        "train_ar": 0.27830082739922046,
        "test_ar": 0.1863828729081778,
        "train_ks": 0.22422322630882263,
        "test_ks": 0.18318483233451843,
        "learning_rate": 0.001,
        "epoch_time_seconds": 0.15413498878479004
      },
      {
        "epoch": 11,
        "train_loss": 0.5924031951210715,
        "test_loss": 0.5940491139888764,
        "train_bce_loss": 0.40805257992310956,
        "train_auc_loss": 0.6714106093753468,
        "test_bce_loss": 0.39909234642982483,
        "test_auc_loss": 0.6776020109653473,
        "train_auc": 0.6401275019072901,
        "test_auc": 0.5990366561691935,
        "train_ar": 0.28025500381458013,
        "test_ar": 0.1980733123383871,
        "train_ks": 0.22615540027618408,
        "test_ks": 0.18902060389518738,
        "learning_rate": 0.001,
        "epoch_time_seconds": 0.1432781219482422
      },
      {
        "epoch": 12,
        "train_loss": 0.5927214432846416,
        "test_loss": 0.593612664937973,
        "train_bce_loss": 0.4092603854157708,
        "train_auc_loss": 0.6713476208123293,
        "test_bce_loss": 0.3965775787830353,
        "test_auc_loss": 0.678056287765503,
        "train_auc": 0.6411998099077207,
        "test_auc": 0.5979507106647718,
        "train_ar": 0.2823996198154415,
        "test_ar": 0.19590142132954358,
        "train_ks": 0.2258538007736206,
        "test_ks": 0.19487997889518738,
        "learning_rate": 0.001,
        "epoch_time_seconds": 0.14528703689575195
      },
      {
        "epoch": 13,
        "train_loss": 0.5895989564332095,
        "test_loss": 0.5935969293117523,
        "train_bce_loss": 0.4020966752008958,
        "train_auc_loss": 0.6699570688334379,
        "test_bce_loss": 0.39662663340568544,
        "test_auc_loss": 0.6780127763748169,
        "train_auc": 0.6423065591097846,
        "test_auc": 0.5963312354125254,
        "train_ar": 0.28461311821956925,
        "test_ar": 0.19266247082505084,
        "train_ks": 0.22254687547683716,
        "test_ks": 0.19224539399147034,
        "learning_rate": 0.001,
        "epoch_time_seconds": 0.15539312362670898
      },
      {
        "epoch": 14,
        "train_loss": 0.5909160429781134,
        "test_loss": 0.5934979856014252,
        "train_bce_loss": 0.40326171300627967,
        "train_auc_loss": 0.6713393384760077,
        "test_bce_loss": 0.3959947913885117,
        "test_auc_loss": 0.6781422138214112,
        "train_auc": 0.6437490376723073,
        "test_auc": 0.5967372846011354,
        "train_ar": 0.2874980753446146,
        "test_ar": 0.1934745692022708,
        "train_ks": 0.22391179203987122,
        "test_ks": 0.20287349820137024,
        "learning_rate": 0.001,
        "epoch_time_seconds": 0.15004801750183105
      },
      {
        "epoch": 15,
        "train_loss": 0.5853485410863702,
        "test_loss": 0.5933537721633911,
        "train_bce_loss": 0.39654476940631866,
        "train_auc_loss": 0.6662644418803129,
        "test_bce_loss": 0.3949062466621399,
        "test_auc_loss": 0.6784027099609375,
        "train_auc": 0.6448323437035116,
        "test_auc": 0.5977697197473683,
        "train_ar": 0.2896646874070232,
        "test_ar": 0.1955394394947365,
        "train_ks": 0.22441130876541138,
        "test_ks": 0.21185851097106934,
        "learning_rate": 0.001,
        "epoch_time_seconds": 0.1371607780456543
      },
      {
        "epoch": 16,
        "train_loss": 0.5858680280772123,
        "test_loss": 0.5934954702854156,
        "train_bce_loss": 0.39554497735066846,
        "train_auc_loss": 0.6674350527199832,
        "test_bce_loss": 0.3946924388408661,
        "test_auc_loss": 0.6786967694759369,
        "train_auc": 0.6459211487501028,
        "test_auc": 0.5961549659973151,
        "train_ar": 0.2918422975002055,
        "test_ar": 0.1923099319946302,
        "train_ks": 0.22488194704055786,
        "test_ks": 0.19701412320137024,
        "learning_rate": 0.001,
        "epoch_time_seconds": 0.16838407516479492
      },
      {
        "epoch": 17,
        "train_loss": 0.5866652537475933,
        "test_loss": 0.5927311539649963,
        "train_bce_loss": 0.39313980124213477,
        "train_auc_loss": 0.6696047403595664,
        "test_bce_loss": 0.39273067712783816,
        "test_auc_loss": 0.6784456431865692,
        "train_auc": 0.6471972097417084,
        "test_auc": 0.5971323169512945,
        "train_ar": 0.2943944194834167,
        "test_ar": 0.19426463390258908,
        "train_ks": 0.2256755232810974,
        "test_ks": 0.1961972713470459,
        "learning_rate": 0.001,
        "epoch_time_seconds": 0.16815805435180664
      },
      {
        "epoch": 18,
        "train_loss": 0.5900783376260237,
        "test_loss": 0.5926796019077301,
        "train_bce_loss": 0.3958030925555663,
        "train_auc_loss": 0.6733391664244912,
        "test_bce_loss": 0.39300053417682645,
        "test_auc_loss": 0.6782563388347626,
        "train_auc": 0.648063883508858,
        "test_auc": 0.5983189878358365,
        "train_ar": 0.29612776701771604,
        "test_ar": 0.19663797567167296,
        "train_ks": 0.2270682454109192,
        "test_ks": 0.18588081002235413,
        "learning_rate": 0.001,
        "epoch_time_seconds": 0.15662407875061035
      },
      {
        "epoch": 19,
        "train_loss": 0.5884838239713148,
        "test_loss": 0.5931331157684326,
        "train_bce_loss": 0.39952201599424536,
        "train_auc_loss": 0.6694674600254406,
        "test_bce_loss": 0.39419929385185243,
        "test_auc_loss": 0.6783904790878296,
        "train_auc": 0.6483111944903339,
        "test_auc": 0.5978035571797523,
        "train_ar": 0.29662238898066784,
        "test_ar": 0.19560711435950462,
        "train_ks": 0.2280181348323822,
        "test_ks": 0.18389779329299927,
        "learning_rate": 0.001,
        "epoch_time_seconds": 0.1467909812927246
      },
      {
        "epoch": 20,
        "train_loss": 0.5828275680541992,
        "test_loss": 0.5937954604625701,
        "train_bce_loss": 0.38764725490049884,
        "train_auc_loss": 0.6664762740785425,
        "test_bce_loss": 0.39543658792972564,
        "test_auc_loss": 0.6788064062595367,
        "train_auc": 0.6496905790868392,
        "test_auc": 0.5963217924081393,
        "train_ar": 0.2993811581736785,
        "test_ar": 0.19264358481627863,
        "train_ks": 0.2322714924812317,
        "test_ks": 0.18786382675170898,
        "learning_rate": 0.001,
        "epoch_time_seconds": 0.14617490768432617
      },
      {
        "epoch": 21,
        "train_loss": 0.5867396024140444,
        "test_loss": 0.5941648602485656,
        "train_bce_loss": 0.39642625234343787,
        "train_auc_loss": 0.6683024655688893,
        "test_bce_loss": 0.3957889288663864,
        "test_auc_loss": 0.6791831254959106,
        "train_auc": 0.650953616094634,
        "test_auc": 0.5947668443525326,
        "train_ar": 0.30190723218926796,
        "test_ar": 0.18953368870506515,
        "train_ks": 0.23330873250961304,
        "test_ks": 0.1900121569633484,
        "learning_rate": 0.001,
        "epoch_time_seconds": 0.1508011817932129
      },
      {
        "epoch": 22,
        "train_loss": 0.5870994464917616,
        "test_loss": 0.5951514303684234,
        "train_bce_loss": 0.394402107054537,
        "train_auc_loss": 0.6696840145371177,
        "test_bce_loss": 0.3976424664258957,
        "test_auc_loss": 0.6797981202602387,
        "train_auc": 0.6511501335392473,
        "test_auc": 0.5909833472617648,
        "train_ar": 0.30230026707849467,
        "test_ar": 0.18196669452352965,
        "train_ks": 0.23581457138061523,
        "test_ks": 0.18711313605308533,
        "learning_rate": 0.001,
        "epoch_time_seconds": 0.14150714874267578
      },
      {
        "epoch": 23,
        "train_loss": 0.587543246420947,
        "test_loss": 0.5940396964550019,
        "train_bce_loss": 0.3950742916627364,
        "train_auc_loss": 0.6700299436395819,
        "test_bce_loss": 0.39732458889484407,
        "test_auc_loss": 0.6783461630344391,
        "train_auc": 0.6510369695910238,
        "test_auc": 0.597047329911818,
        "train_ar": 0.3020739391820475,
        "test_ar": 0.19409465982363594,
        "train_ks": 0.2316526472568512,
        "test_ks": 0.1869620680809021,
        "learning_rate": 0.001,
        "epoch_time_seconds": 0.15053796768188477
      },
      {
        "epoch": 24,
        "train_loss": 0.5864867242899808,
        "test_loss": 0.5943370401859284,
        "train_bce_loss": 0.3960138342597268,
        "train_auc_loss": 0.6681179648095911,
        "test_bce_loss": 0.397261369228363,
        "test_auc_loss": 0.6787980675697327,
        "train_auc": 0.6515249348511387,
        "test_auc": 0.5957457691405764,
        "train_ar": 0.30304986970227743,
        "test_ar": 0.19149153828115284,
        "train_ks": 0.23421576619148254,
        "test_ks": 0.1943039894104004,
        "learning_rate": 0.0005,
        "epoch_time_seconds": 0.14299297332763672
      },
      {
        "epoch": 25,
        "train_loss": 0.5852189985188571,
        "test_loss": 0.5941991150379181,
        "train_bce_loss": 0.39307783814993774,
        "train_auc_loss": 0.6675652102990584,
        "test_bce_loss": 0.39744009673595426,
        "test_auc_loss": 0.6785244107246399,
        "train_auc": 0.6516305738309383,
        "test_auc": 0.596225788530212,
        "train_ar": 0.3032611476618765,
        "test_ar": 0.19245157706042404,
        "train_ks": 0.23219618201255798,
        "test_ks": 0.19280725717544556,
        "learning_rate": 0.0005,
        "epoch_time_seconds": 0.20293593406677246
      },
      {
        "epoch": 26,
        "train_loss": 0.5830009796402671,
        "test_loss": 0.5943314433097839,
        "train_bce_loss": 0.3909697207537564,
        "train_auc_loss": 0.6653000847859816,
        "test_bce_loss": 0.39757768511772157,
        "test_auc_loss": 0.6786544799804688,
        "train_auc": 0.6520988584044056,
        "test_auc": 0.5952201085630737,
        "train_ar": 0.30419771680881125,
        "test_ar": 0.19044021712614745,
        "train_ks": 0.23235657811164856,
        "test_ks": 0.18858152627944946,
        "learning_rate": 0.0005,
        "epoch_time_seconds": 0.15240001678466797
      },
      {
        "epoch": 27,
        "train_loss": 0.5810329128395427,
        "test_loss": 0.5945343732833862,
        "train_bce_loss": 0.38746729628606275,
        "train_auc_loss": 0.663989622484554,
        "test_bce_loss": 0.398401141166687,
        "test_auc_loss": 0.6785914778709412,
        "train_auc": 0.6521095670133168,
        "test_auc": 0.5944662420462361,
        "train_ar": 0.3042191340266336,
        "test_ar": 0.1889324840924722,
        "train_ks": 0.23415619134902954,
        "test_ks": 0.18970999121665955,
        "learning_rate": 0.0005,
        "epoch_time_seconds": 0.15177106857299805
      },
      {
        "epoch": 28,
        "train_loss": 0.5854384844953363,
        "test_loss": 0.5944055199623108,
        "train_bce_loss": 0.3937255780805241,
        "train_auc_loss": 0.667601162737066,
        "test_bce_loss": 0.39756172001361845,
        "test_auc_loss": 0.6787671506404876,
        "train_auc": 0.6525908755705951,
        "test_auc": 0.5945811319329358,
        "train_ar": 0.3051817511411903,
        "test_ar": 0.18916226386587165,
        "train_ks": 0.23636212944984436,
        "test_ks": 0.19228318333625793,
        "learning_rate": 0.0005,
        "epoch_time_seconds": 0.15732312202453613
      },
      {
        "epoch": 29,
        "train_loss": 0.5870673764835704,
        "test_loss": 0.5939766705036164,
        "train_bce_loss": 0.39490293101830914,
        "train_auc_loss": 0.6694235693324696,
        "test_bce_loss": 0.3971076548099518,
        "test_auc_loss": 0.6783490896224975,
        "train_auc": 0.6526299475220279,
        "test_auc": 0.5962682820499503,
        "train_ar": 0.3052598950440557,
        "test_ar": 0.1925365640999006,
        "train_ks": 0.24194854497909546,
        "test_ks": 0.18347284197807312,
        "learning_rate": 0.0005,
        "epoch_time_seconds": 0.13584113121032715
      },
      {
        "epoch": 30,
        "train_loss": 0.5854571813886816,
        "test_loss": 0.5941504240036011,
        "train_bce_loss": 0.39432535659183154,
        "train_auc_loss": 0.6673708260059357,
        "test_bce_loss": 0.3975993812084198,
        "test_auc_loss": 0.6783865749835968,
        "train_auc": 0.6528577225277874,
        "test_auc": 0.5956749466076794,
        "train_ar": 0.3057154450555748,
        "test_ar": 0.19134989321535878,
        "train_ks": 0.24094083905220032,
        "test_ks": 0.1864852011203766,
        "learning_rate": 0.00025,
        "epoch_time_seconds": 0.14607715606689453
      },
      {
        "epoch": 31,
        "train_loss": 0.583263402635401,
        "test_loss": 0.5939793050289154,
        "train_bce_loss": 0.3906562761826949,
        "train_auc_loss": 0.6658093116500161,
        "test_bce_loss": 0.3977533459663391,
        "test_auc_loss": 0.6780761301517486,
        "train_auc": 0.6527659757973862,
        "test_auc": 0.5968993895097665,
        "train_ar": 0.3055319515947723,
        "test_ar": 0.19379877901953302,
        "train_ks": 0.23951050639152527,
        "test_ks": 0.18436521291732788,
        "learning_rate": 0.00025,
        "epoch_time_seconds": 0.14975214004516602
      },
      {
        "epoch": 32,
        "train_loss": 0.5848151526667855,
        "test_loss": 0.5941192150115967,
        "train_bce_loss": 0.3920230242339047,
        "train_auc_loss": 0.667440343986858,
        "test_bce_loss": 0.3972014307975769,
        "test_auc_loss": 0.678512555360794,
        "train_auc": 0.6533766559271861,
        "test_auc": 0.5958590851932117,
        "train_ar": 0.30675331185437216,
        "test_ar": 0.19171817038642347,
        "train_ks": 0.23974260687828064,
        "test_ks": 0.18740114569664001,
        "learning_rate": 0.00025,
        "epoch_time_seconds": 0.14124107360839844
      },
      {
        "epoch": 33,
        "train_loss": 0.5882619402625344,
        "test_loss": 0.5942923486232757,
        "train_bce_loss": 0.3982898660681464,
        "train_auc_loss": 0.6696785552935167,
        "test_bce_loss": 0.39745078086853025,
        "test_auc_loss": 0.6786530196666718,
        "train_auc": 0.6535339567094356,
        "test_auc": 0.595361753628868,
        "train_ar": 0.3070679134188712,
        "test_ar": 0.190723507257736,
        "train_ks": 0.24054604768753052,
        "test_ks": 0.19319912791252136,
        "learning_rate": 0.00025,
        "epoch_time_seconds": 0.14315319061279297
      },
      {
        "epoch": 34,
        "train_loss": 0.5861920524727214,
        "test_loss": 0.5940141975879669,
        "train_bce_loss": 0.3934020129117099,
        "train_auc_loss": 0.6688163415952162,
        "test_bce_loss": 0.3970125764608383,
        "test_auc_loss": 0.6784434735774993,
        "train_auc": 0.6536892315386477,
        "test_auc": 0.5961124724775768,
        "train_ar": 0.3073784630772953,
        "test_ar": 0.19222494495515363,
        "train_ks": 0.2411729097366333,
        "test_ks": 0.18898287415504456,
        "learning_rate": 0.00025,
        "epoch_time_seconds": 0.15001177787780762
      },
      {
        "epoch": 35,
        "train_loss": 0.5845586820082231,
        "test_loss": 0.5940774500370025,
        "train_bce_loss": 0.3919424604285847,
        "train_auc_loss": 0.6671084842898629,
        "test_bce_loss": 0.3969563037157059,
        "test_auc_loss": 0.6785579442977905,
        "train_auc": 0.653946816996241,
        "test_auc": 0.5954640528430526,
        "train_ar": 0.30789363399248204,
        "test_ar": 0.1909281056861052,
        "train_ks": 0.23851430416107178,
        "test_ks": 0.18755227327346802,
        "learning_rate": 0.00025,
        "epoch_time_seconds": 0.14605283737182617
      },
      {
        "epoch": 36,
        "train_loss": 0.5890613658861681,
        "test_loss": 0.594046688079834,
        "train_bce_loss": 0.3986904445019635,
        "train_auc_loss": 0.6706489026546478,
        "test_bce_loss": 0.3969173491001129,
        "test_auc_loss": 0.6785306870937348,
        "train_auc": 0.6540440627420291,
        "test_auc": 0.5953948041442199,
        "train_ar": 0.3080881254840582,
        "test_ar": 0.19078960828843972,
        "train_ks": 0.23931774497032166,
        "test_ks": 0.18631049990653992,
        "learning_rate": 0.000125,
        "epoch_time_seconds": 0.1416797637939453
      },
      {
        "epoch": 37,
        "train_loss": 0.587371132590554,
        "test_loss": 0.5941608548164368,
        "train_bce_loss": 0.39416851509701123,
        "train_auc_loss": 0.6701722605661913,
        "test_bce_loss": 0.39715082943439484,
        "test_auc_loss": 0.6785937368869781,
        "train_auc": 0.6541308893007683,
        "test_auc": 0.5951429906939192,
        "train_ar": 0.3082617786015367,
        "test_ar": 0.19028598138783837,
        "train_ks": 0.2396036982536316,
        "test_ks": 0.19459202885627747,
        "learning_rate": 0.000125,
        "epoch_time_seconds": 0.15212631225585938
      },
      {
        "epoch": 38,
        "train_loss": 0.5841826688159596,
        "test_loss": 0.5940136194229126,
        "train_bce_loss": 0.3909793590957468,
        "train_auc_loss": 0.6669840866869147,
        "test_bce_loss": 0.397176530957222,
        "test_auc_loss": 0.6783723711967469,
        "train_auc": 0.6540388531485046,
        "test_auc": 0.5955616305550441,
        "train_ar": 0.30807770629700926,
        "test_ar": 0.19112326111008815,
        "train_ks": 0.24118679761886597,
        "test_ks": 0.18831709027290344,
        "learning_rate": 0.000125,
        "epoch_time_seconds": 0.14315485954284668
      },
      {
        "epoch": 39,
        "train_loss": 0.5855525894598528,
        "test_loss": 0.5940706253051757,
        "train_bce_loss": 0.3921060304750096,
        "train_auc_loss": 0.668458258563822,
        "test_bce_loss": 0.39714759588241577,
        "test_auc_loss": 0.6784662008285522,
        "train_auc": 0.6541621468619145,
        "test_auc": 0.595054855986314,
        "train_ar": 0.3083242937238291,
        "test_ar": 0.19010971197262805,
        "train_ks": 0.23819127678871155,
        "test_ks": 0.18597054481506348,
        "learning_rate": 0.000125,
        "epoch_time_seconds": 0.1421051025390625
      },
      {
        "epoch": 40,
        "train_loss": 0.5813585628162731,
        "test_loss": 0.5940847218036651,
        "train_bce_loss": 0.38724442503669043,
        "train_auc_loss": 0.6645503342151642,
        "test_bce_loss": 0.3968251347541809,
        "test_auc_loss": 0.6786245405673981,
        "train_auc": 0.654626090107445,
        "test_auc": 0.5946535282998973,
        "train_ar": 0.30925218021489,
        "test_ar": 0.18930705659979452,
        "train_ks": 0.24258935451507568,
        "test_ks": 0.1852056384086609,
        "learning_rate": 0.000125,
        "epoch_time_seconds": 0.14744186401367188
      },
      {
        "epoch": 41,
        "train_loss": 0.5824509479782798,
        "test_loss": 0.594101470708847,
        "train_bce_loss": 0.38873020762746985,
        "train_auc_loss": 0.6654741303487257,
        "test_bce_loss": 0.397148522734642,
        "test_auc_loss": 0.6785098850727082,
        "train_auc": 0.6545699422661269,
        "test_auc": 0.5949903287896743,
        "train_ar": 0.3091398845322537,
        "test_ar": 0.18998065757934857,
        "train_ks": 0.23854205012321472,
        "test_ks": 0.18307152390480042,
        "learning_rate": 0.000125,
        "epoch_time_seconds": 0.16116881370544434
      },
      {
        "epoch": 42,
        "train_loss": 0.5843013850125399,
        "test_loss": 0.5941123127937317,
        "train_bce_loss": 0.39081335880539636,
        "train_auc_loss": 0.6672248271378604,
        "test_bce_loss": 0.39726031124591826,
        "test_auc_loss": 0.6784774720668793,
        "train_auc": 0.6545158203778461,
        "test_auc": 0.5954372976639581,
        "train_ar": 0.3090316407556921,
        "test_ar": 0.19087459532791629,
        "train_ks": 0.239303857088089,
        "test_ks": 0.1822310984134674,
        "learning_rate": 6.25e-05,
        "epoch_time_seconds": 0.14008688926696777
      },
      {
        "epoch": 43,
        "train_loss": 0.5803805535489862,
        "test_loss": 0.5940747261047363,
        "train_bce_loss": 0.3859272748231888,
        "train_auc_loss": 0.6637176817113702,
        "test_bce_loss": 0.39668938219547273,
        "test_auc_loss": 0.6786684453487396,
        "train_auc": 0.6547308608216571,
        "test_auc": 0.5950044932962537,
        "train_ar": 0.3094617216433142,
        "test_ar": 0.19000898659250742,
        "train_ks": 0.24096858501434326,
        "test_ks": 0.1818675398826599,
        "learning_rate": 6.25e-05,
        "epoch_time_seconds": 0.1365809440612793
      },
      {
        "epoch": 44,
        "train_loss": 0.5848225219683214,
        "test_loss": 0.594108498096466,
        "train_bce_loss": 0.39011247727003967,
        "train_auc_loss": 0.668269693851471,
        "test_bce_loss": 0.396757972240448,
        "test_auc_loss": 0.678687310218811,
        "train_auc": 0.6545971479211986,
        "test_auc": 0.5950642989907002,
        "train_ar": 0.3091942958423972,
        "test_ar": 0.19012859798140047,
        "train_ks": 0.2416093945503235,
        "test_ks": 0.18406304717063904,
        "learning_rate": 6.25e-05,
        "epoch_time_seconds": 0.1424729824066162
      },
      {
        "epoch": 45,
        "train_loss": 0.583035721020265,
        "test_loss": 0.5941140711307525,
        "train_bce_loss": 0.3899369632655924,
        "train_auc_loss": 0.6657923351634633,
        "test_bce_loss": 0.39682263433933257,
        "test_auc_loss": 0.67866752743721,
        "train_auc": 0.6547294137123447,
        "test_auc": 0.5947935995316269,
        "train_ar": 0.30945882742468944,
        "test_ar": 0.18958719906325383,
        "train_ks": 0.24083369970321655,
        "test_ks": 0.1853567361831665,
        "learning_rate": 6.25e-05,
        "epoch_time_seconds": 0.14559173583984375
      },
      {
        "epoch": 46,
        "train_loss": 0.5843758501789786,
        "test_loss": 0.5941248536109924,
        "train_bce_loss": 0.3907336782325398,
        "train_auc_loss": 0.6673653586344286,
        "test_bce_loss": 0.39710459411144255,
        "test_auc_loss": 0.6785620987415314,
        "train_auc": 0.6549033562516858,
        "test_auc": 0.5951996487202368,
        "train_ar": 0.30980671250337166,
        "test_ar": 0.19039929744047357,
        "train_ks": 0.23859992623329163,
        "test_ks": 0.18270796537399292,
        "learning_rate": 6.25e-05,
        "epoch_time_seconds": 0.15363407135009766
      },
      {
        "epoch": 47,
        "train_loss": 0.5835732167417352,
        "test_loss": 0.5942632555961609,
        "train_bce_loss": 0.3907736607573249,
        "train_auc_loss": 0.6662015996196053,
        "test_bce_loss": 0.39786804020404815,
        "test_auc_loss": 0.6784326195716858,
        "train_auc": 0.6546683456993648,
        "test_auc": 0.5949069155842622,
        "train_ar": 0.30933669139872966,
        "test_ar": 0.18981383116852446,
        "train_ks": 0.24158158898353577,
        "test_ks": 0.18406304717063904,
        "learning_rate": 6.25e-05,
        "epoch_time_seconds": 0.19533634185791016
      },
      {
        "epoch": 48,
        "train_loss": 0.5853413912382993,
        "test_loss": 0.5942388892173767,
        "train_bce_loss": 0.39189783280546014,
        "train_auc_loss": 0.6682457734238018,
        "test_bce_loss": 0.3972806304693222,
        "test_auc_loss": 0.6786495745182037,
        "train_auc": 0.6548509708945798,
        "test_auc": 0.5945307692428756,
        "train_ar": 0.30970194178915955,
        "test_ar": 0.18906153848575125,
        "train_ks": 0.2442517876625061,
        "test_ks": 0.1908525824546814,
        "learning_rate": 3.125e-05,
        "epoch_time_seconds": 0.1532433032989502
      },
      {
        "epoch": 49,
        "train_loss": 0.584501017223705,
        "test_loss": 0.5942544043064117,
        "train_bce_loss": 0.3899455720728094,
        "train_auc_loss": 0.6678819304162805,
        "test_bce_loss": 0.3973963141441345,
        "test_auc_loss": 0.6786221623420715,
        "train_auc": 0.6549155119699095,
        "test_auc": 0.5946377899592534,
        "train_ar": 0.309831023939819,
        "test_ar": 0.18927557991850685,
        "train_ks": 0.24101027846336365,
        "test_ks": 0.190739244222641,
        "learning_rate": 3.125e-05,
        "epoch_time_seconds": 0.14173531532287598
      },
      {
        "epoch": 50,
        "train_loss": 0.5816322808915918,
        "test_loss": 0.5943721950054168,
        "train_bce_loss": 0.3875320472500541,
        "train_auc_loss": 0.6648180945353075,
        "test_bce_loss": 0.39769016206264496,
        "test_auc_loss": 0.67866450548172,
        "train_auc": 0.6547192839471585,
        "test_auc": 0.5945543767538413,
        "train_ar": 0.309438567894317,
        "test_ar": 0.18910875350768253,
        "train_ks": 0.2403532862663269,
        "test_ks": 0.18711313605308533,
        "learning_rate": 3.125e-05,
        "epoch_time_seconds": 0.1385209560394287
      },
      {
        "epoch": 51,
        "train_loss": 0.5800413868644021,
        "test_loss": 0.5943765282630921,
        "train_bce_loss": 0.38542965189977124,
        "train_auc_loss": 0.6634464209729974,
        "test_bce_loss": 0.39774938821792605,
        "test_auc_loss": 0.6786453068256378,
        "train_auc": 0.654918985032259,
        "test_auc": 0.5944512906226245,
        "train_ar": 0.30983797006451796,
        "test_ar": 0.18890258124524895,
        "train_ks": 0.24216681718826294,
        "test_ks": 0.1908147633075714,
        "learning_rate": 3.125e-05,
        "epoch_time_seconds": 0.1559150218963623
      },
      {
        "epoch": 52,
        "train_loss": 0.5786715664646842,
        "test_loss": 0.5943015217781067,
        "train_bce_loss": 0.38492409749464557,
        "train_auc_loss": 0.6617061956362291,
        "test_bce_loss": 0.3972975522279739,
        "test_auc_loss": 0.6787317991256714,
        "train_auc": 0.6549942347164998,
        "test_auc": 0.5942049855915491,
        "train_ar": 0.3099884694329995,
        "test_ar": 0.1884099711830982,
        "train_ks": 0.24175816774368286,
        "test_ks": 0.18501678109169006,
        "learning_rate": 3.125e-05,
        "epoch_time_seconds": 0.14536094665527344
      },
      {
        "epoch": 53,
        "train_loss": 0.5859260748733174,
        "test_loss": 0.5942860245704651,
        "train_bce_loss": 0.393232291395014,
        "train_auc_loss": 0.6685091257095337,
        "test_bce_loss": 0.39713763296604154,
        "test_auc_loss": 0.6787781774997711,
        "train_auc": 0.6550744045724024,
        "test_auc": 0.5942931202991544,
        "train_ar": 0.3101488091448048,
        "test_ar": 0.18858624059830875,
        "train_ks": 0.2432023584842682,
        "test_ks": 0.18890729546546936,
        "learning_rate": 3.125e-05,
        "epoch_time_seconds": 0.1398172378540039
      },
      {
        "epoch": 54,
        "train_loss": 0.5882830375974829,
        "test_loss": 0.5942724227905274,
        "train_bce_loss": 0.3958447440104051,
        "train_auc_loss": 0.6707565974105488,
        "test_bce_loss": 0.39733831882476806,
        "test_auc_loss": 0.6786727607250214,
        "train_auc": 0.6549181167666716,
        "test_auc": 0.5942695127881887,
        "train_ar": 0.3098362335333431,
        "test_ar": 0.18853902557637747,
        "train_ks": 0.24203193187713623,
        "test_ks": 0.18600833415985107,
        "learning_rate": 1.5625e-05,
        "epoch_time_seconds": 0.13454413414001465
      },
      {
        "epoch": 55,
        "train_loss": 0.5850182636217638,
        "test_loss": 0.594364583492279,
        "train_bce_loss": 0.39128075404600665,
        "train_auc_loss": 0.6680486256426031,
        "test_bce_loss": 0.3976803570985794,
        "test_auc_loss": 0.6786578238010407,
        "train_auc": 0.6550331619570011,
        "test_auc": 0.5941530490674246,
        "train_ar": 0.31006632391400224,
        "test_ar": 0.18830609813484922,
        "train_ks": 0.24256154894828796,
        "test_ks": 0.18549364805221558,
        "learning_rate": 1.5625e-05,
        "epoch_time_seconds": 0.16245722770690918
      },
      {
        "epoch": 56,
        "train_loss": 0.5829397981817072,
        "test_loss": 0.5943314075469971,
        "train_bce_loss": 0.39098175818269904,
        "train_auc_loss": 0.6652075323191556,
        "test_bce_loss": 0.3974365770816803,
        "test_auc_loss": 0.678714907169342,
        "train_auc": 0.6550842449157261,
        "test_auc": 0.5940995387092358,
        "train_ar": 0.3101684898314523,
        "test_ar": 0.18819907741847164,
        "train_ks": 0.2421807050704956,
        "test_ks": 0.18556919693946838,
        "learning_rate": 1.5625e-05,
        "epoch_time_seconds": 0.1520528793334961
      },
      {
        "epoch": 57,
        "train_loss": 0.5870533097874034,
        "test_loss": 0.5943108201026917,
        "train_bce_loss": 0.39480667358094995,
        "train_auc_loss": 0.6694447208534587,
        "test_bce_loss": 0.39712136089801786,
        "test_auc_loss": 0.6788205802440643,
        "train_auc": 0.6552516754631618,
        "test_auc": 0.59431672781012,
        "train_ar": 0.31050335092632353,
        "test_ar": 0.18863345562024003,
        "train_ks": 0.24521785974502563,
        "test_ks": 0.18850600719451904,
        "learning_rate": 1.5625e-05,
        "epoch_time_seconds": 0.17921996116638184
      },
      {
        "epoch": 58,
        "train_loss": 0.5834904096343301,
        "test_loss": 0.5943489968776703,
        "train_bce_loss": 0.3902923261577433,
        "train_auc_loss": 0.666289592331106,
        "test_bce_loss": 0.39730594754219056,
        "test_auc_loss": 0.678796011209488,
        "train_auc": 0.6552376385028322,
        "test_auc": 0.5940357984296283,
        "train_ar": 0.31047527700566446,
        "test_ar": 0.18807159685925656,
        "train_ks": 0.2425754964351654,
        "test_ks": 0.18513011932373047,
        "learning_rate": 1.5625e-05,
        "epoch_time_seconds": 0.1549828052520752
      },
      {
        "epoch": 59,
        "train_loss": 0.5805676227266138,
        "test_loss": 0.5943800270557403,
        "train_bce_loss": 0.3871392458677292,
        "train_auc_loss": 0.6634655052965338,
        "test_bce_loss": 0.39786486625671386,
        "test_auc_loss": 0.678600811958313,
        "train_auc": 0.6549673184832905,
        "test_auc": 0.5942695127881887,
        "train_ar": 0.30993463696658097,
        "test_ar": 0.18853902557637747,
        "train_ks": 0.24238502979278564,
        "test_ks": 0.18835487961769104,
        "learning_rate": 1.5625e-05,
        "epoch_time_seconds": 0.14564299583435059
      },
      {
        "epoch": 60,
        "train_loss": 0.583604021505876,
        "test_loss": 0.5943456709384918,
        "train_bce_loss": 0.3920745009725744,
        "train_auc_loss": 0.6656881056048654,
        "test_bce_loss": 0.3975165605545044,
        "test_auc_loss": 0.6787010133266449,
        "train_auc": 0.6549872885918006,
        "test_auc": 0.5943741727534699,
        "train_ar": 0.3099745771836011,
        "test_ar": 0.18874834550693986,
        "train_ks": 0.2420041263103485,
        "test_ks": 0.19184410572052002,
        "learning_rate": 7.8125e-06,
        "epoch_time_seconds": 0.14191412925720215
      },
      {
        "epoch": 61,
        "train_loss": 0.5826637121764097,
        "test_loss": 0.5942848503589631,
        "train_bce_loss": 0.389271463860165,
        "train_auc_loss": 0.665546094829386,
        "test_bce_loss": 0.39749398827552795,
        "test_auc_loss": 0.6786237955093384,
        "train_auc": 0.6549568992962418,
        "test_auc": 0.5946377899592534,
        "train_ar": 0.3099137985924836,
        "test_ar": 0.18927557991850685,
        "train_ks": 0.24017906188964844,
        "test_ks": 0.1869620680809021,
        "learning_rate": 7.8125e-06,
        "epoch_time_seconds": 0.14152979850769043
      },
      {
        "epoch": 62,
        "train_loss": 0.5828375545415011,
        "test_loss": 0.5942402482032776,
        "train_bce_loss": 0.39141449196772143,
        "train_auc_loss": 0.6648760112849149,
        "test_bce_loss": 0.397292760014534,
        "test_auc_loss": 0.678646320104599,
        "train_auc": 0.65505298735458,
        "test_auc": 0.5944977187275238,
        "train_ar": 0.3101059747091599,
        "test_ar": 0.18899543745504754,
        "train_ks": 0.24361103773117065,
        "test_ks": 0.18354839086532593,
        "learning_rate": 7.8125e-06,
        "epoch_time_seconds": 0.1590561866760254
      },
      {
        "epoch": 63,
        "train_loss": 0.580531510439786,
        "test_loss": 0.5944556057453155,
        "train_bce_loss": 0.386904008009217,
        "train_auc_loss": 0.6635147333145142,
        "test_bce_loss": 0.39804819226264954,
        "test_auc_loss": 0.6786302149295806,
        "train_auc": 0.6550237557464711,
        "test_auc": 0.5941514752333603,
        "train_ar": 0.3100475114929422,
        "test_ar": 0.18830295046672063,
        "train_ks": 0.24200180172920227,
        "test_ks": 0.18516790866851807,
        "learning_rate": 7.8125e-06,
        "epoch_time_seconds": 0.1598808765411377
      },
      {
        "epoch": 64,
        "train_loss": 0.5875030945647847,
        "test_loss": 0.5942524552345276,
        "train_bce_loss": 0.3949507393620231,
        "train_auc_loss": 0.6700255356051705,
        "test_bce_loss": 0.39709470272064207,
        "test_auc_loss": 0.6787486374378204,
        "train_auc": 0.6552787364073023,
        "test_auc": 0.5944253223605622,
        "train_ar": 0.31055747281460455,
        "test_ar": 0.18885064472112445,
        "train_ks": 0.24053215980529785,
        "test_ks": 0.18597054481506348,
        "learning_rate": 7.8125e-06,
        "epoch_time_seconds": 0.1431419849395752
      },
      {
        "epoch": 65,
        "train_loss": 0.5837555500594053,
        "test_loss": 0.5942999184131622,
        "train_bce_loss": 0.3907511816783385,
        "train_auc_loss": 0.6664717197418213,
        "test_bce_loss": 0.3975935339927673,
        "test_auc_loss": 0.678602659702301,
        "train_auc": 0.6549898933885627,
        "test_auc": 0.5944709635484292,
        "train_ar": 0.30997978677712545,
        "test_ar": 0.18894192709685842,
        "train_ks": 0.2428075671195984,
        "test_ks": 0.18600833415985107,
        "learning_rate": 7.8125e-06,
        "epoch_time_seconds": 0.1523430347442627
      },
      {
        "epoch": 66,
        "train_loss": 0.5838643718849529,
        "test_loss": 0.5942732632160187,
        "train_bce_loss": 0.39009379663250665,
        "train_auc_loss": 0.6669089062647386,
        "test_bce_loss": 0.39735129177570344,
        "test_auc_loss": 0.6786683976650238,
        "train_auc": 0.6551793199975458,
        "test_auc": 0.5944725373824936,
        "train_ar": 0.3103586399950915,
        "test_ar": 0.18894507476498723,
        "train_ks": 0.24215289950370789,
        "test_ks": 0.1864852011203766,
        "learning_rate": 3.90625e-06,
        "epoch_time_seconds": 0.14492201805114746
      },
      {
        "epoch": 67,
        "train_loss": 0.5816028361970728,
        "test_loss": 0.5942313313484192,
        "train_bce_loss": 0.38795678317546844,
        "train_auc_loss": 0.6645940108732744,
        "test_bce_loss": 0.39660704135894775,
        "test_auc_loss": 0.6789274573326111,
        "train_auc": 0.6553629581692794,
        "test_auc": 0.5941923949190341,
        "train_ar": 0.3107259163385587,
        "test_ar": 0.18838478983806817,
        "train_ks": 0.24321624636650085,
        "test_ks": 0.1874389350414276,
        "learning_rate": 3.90625e-06,
        "epoch_time_seconds": 0.1421051025390625
      },
      {
        "epoch": 68,
        "train_loss": 0.5839245210994374,
        "test_loss": 0.5943517625331879,
        "train_bce_loss": 0.3905706148255955,
        "train_auc_loss": 0.6667904826727781,
        "test_bce_loss": 0.3971630781888962,
        "test_auc_loss": 0.6788611948490143,
        "train_auc": 0.6552263510501961,
        "test_auc": 0.5939091047874459,
        "train_ar": 0.3104527021003922,
        "test_ar": 0.1878182095748917,
        "train_ks": 0.24159544706344604,
        "test_ks": 0.18787801265716553,
        "learning_rate": 3.90625e-06,
        "epoch_time_seconds": 0.1348280906677246
      },
      {
        "epoch": 69,
        "train_loss": 0.5852076519619335,
        "test_loss": 0.5943017840385437,
        "train_bce_loss": 0.39314173703843897,
        "train_auc_loss": 0.6675216095014052,
        "test_bce_loss": 0.3970496207475662,
        "test_auc_loss": 0.6788384139537811,
        "train_auc": 0.6553264910146088,
        "test_auc": 0.5940751442812379,
        "train_ar": 0.31065298202921765,
        "test_ar": 0.18815028856247573,
        "train_ks": 0.2428075671195984,
        "test_ks": 0.18894508481025696,
        "learning_rate": 3.90625e-06,
        "epoch_time_seconds": 0.1504528522491455
      },
      {
        "epoch": 70,
        "train_loss": 0.5800237493081526,
        "test_loss": 0.5942583680152893,
        "train_bce_loss": 0.3841805403882807,
        "train_auc_loss": 0.6639565337787975,
        "test_bce_loss": 0.39741782546043397,
        "test_auc_loss": 0.678618586063385,
        "train_auc": 0.6550535661983049,
        "test_auc": 0.5944772588846867,
        "train_ar": 0.3101071323966098,
        "test_ar": 0.18895451776937344,
        "train_ks": 0.24194854497909546,
        "test_ks": 0.18600833415985107,
        "learning_rate": 3.90625e-06,
        "epoch_time_seconds": 0.21043896675109863
      },
      {
        "epoch": 71,
        "train_loss": 0.5841659009456635,
        "test_loss": 0.5942209601402283,
        "train_bce_loss": 0.3916655318303542,
        "train_auc_loss": 0.6666660498489033,
        "test_bce_loss": 0.3967646867036819,
        "test_auc_loss": 0.6788450717926026,
        "train_auc": 0.6553953734178753,
        "test_auc": 0.5943718120023733,
        "train_ar": 0.3107907468357507,
        "test_ar": 0.18874362400474665,
        "train_ks": 0.2412007451057434,
        "test_ks": 0.18886956572532654,
        "learning_rate": 3.90625e-06,
        "epoch_time_seconds": 0.14728689193725586
      },
      {
        "epoch": 72,
        "train_loss": 0.5855408717285503,
        "test_loss": 0.594374668598175,
        "train_bce_loss": 0.3916668932546269,
        "train_auc_loss": 0.6686297167431224,
        "test_bce_loss": 0.39736871123313905,
        "test_auc_loss": 0.6788057863712311,
        "train_auc": 0.6550671690258407,
        "test_auc": 0.593951598307184,
        "train_ar": 0.31013433805168145,
        "test_ar": 0.18790319661436805,
        "train_ks": 0.2415931522846222,
        "test_ks": 0.18362396955490112,
        "learning_rate": 1.953125e-06,
        "epoch_time_seconds": 0.14854121208190918
      },
      {
        "epoch": 73,
        "train_loss": 0.5844416618347168,
        "test_loss": 0.5942928850650787,
        "train_bce_loss": 0.39136444574052637,
        "train_auc_loss": 0.6671890372579748,
        "test_bce_loss": 0.39726643860340116,
        "test_auc_loss": 0.6787328004837037,
        "train_auc": 0.6551176731408408,
        "test_auc": 0.5944457822033992,
        "train_ar": 0.3102353462816816,
        "test_ar": 0.18889156440679833,
        "train_ks": 0.23967716097831726,
        "test_ks": 0.1874389350414276,
        "learning_rate": 1.953125e-06,
        "epoch_time_seconds": 0.14312100410461426
      },
      {
        "epoch": 74,
        "train_loss": 0.5849342860958793,
        "test_loss": 0.5942859530448914,
        "train_bce_loss": 0.39316830039024353,
        "train_auc_loss": 0.6671197089281949,
        "test_bce_loss": 0.39716917276382446,
        "test_auc_loss": 0.6787645876407623,
        "train_auc": 0.6553180977805974,
        "test_auc": 0.594167213574004,
        "train_ar": 0.3106361955611947,
        "test_ar": 0.18833442714800808,
        "train_ks": 0.24301189184188843,
        "test_ks": 0.18711313605308533,
        "learning_rate": 1.953125e-06,
        "epoch_time_seconds": 0.14371395111083984
      },
      {
        "epoch": 75,
        "train_loss": 0.585242981260473,
        "test_loss": 0.594365656375885,
        "train_bce_loss": 0.3935566964474591,
        "train_auc_loss": 0.6673942452127283,
        "test_bce_loss": 0.3973646640777588,
        "test_auc_loss": 0.678794664144516,
        "train_auc": 0.6551864108331761,
        "test_auc": 0.5939106786215101,
        "train_ar": 0.31037282166635216,
        "test_ar": 0.1878213572430203,
        "train_ks": 0.24108728766441345,
        "test_ks": 0.18890729546546936,
        "learning_rate": 1.953125e-06,
        "epoch_time_seconds": 0.1388700008392334
      },
      {
        "epoch": 76,
        "train_loss": 0.5851128074255857,
        "test_loss": 0.5943895757198334,
        "train_bce_loss": 0.3936147798191417,
        "train_auc_loss": 0.6671833883632313,
        "test_bce_loss": 0.39701187908649443,
        "test_auc_loss": 0.678980004787445,
        "train_auc": 0.6552341654404827,
        "test_auc": 0.5936226669877287,
        "train_ar": 0.3104683308809655,
        "test_ar": 0.1872453339754574,
        "train_ks": 0.24159544706344604,
        "test_ks": 0.1869242787361145,
        "learning_rate": 1.953125e-06,
        "epoch_time_seconds": 0.15520691871643066
      },
      {
        "epoch": 77,
        "train_loss": 0.5828816782344471,
        "test_loss": 0.5942072331905365,
        "train_bce_loss": 0.3907158239321275,
        "train_auc_loss": 0.665238464420492,
        "test_bce_loss": 0.39674018025398256,
        "test_auc_loss": 0.6788359820842743,
        "train_auc": 0.6553335818502392,
        "test_auc": 0.5941672135740039,
        "train_ar": 0.3106671637004783,
        "test_ar": 0.18833442714800785,
        "train_ks": 0.24179980158805847,
        "test_ks": 0.18553146719932556,
        "learning_rate": 1.953125e-06,
        "epoch_time_seconds": 0.14420199394226074
      },
      {
        "epoch": 78,
        "train_loss": 0.5864631289785559,
        "test_loss": 0.5943503558635712,
        "train_bce_loss": 0.3942751356146552,
        "train_auc_loss": 0.6688294058496301,
        "test_bce_loss": 0.3975081443786621,
        "test_auc_loss": 0.6787113070487976,
        "train_auc": 0.6551068198209984,
        "test_auc": 0.5943670905001802,
        "train_ar": 0.3102136396419968,
        "test_ar": 0.18873418100036043,
        "train_ks": 0.2450135350227356,
        "test_ks": 0.18740114569664001,
        "learning_rate": 9.765625e-07,
        "epoch_time_seconds": 0.1442270278930664
      },
      {
        "epoch": 79,
        "train_loss": 0.5812257826328278,
        "test_loss": 0.5942536234855652,
        "train_bce_loss": 0.38721020926128735,
        "train_auc_loss": 0.6643753105943854,
        "test_bce_loss": 0.39708645939826964,
        "test_auc_loss": 0.6787538409233094,
        "train_auc": 0.6552717902826031,
        "test_auc": 0.5943387614870214,
        "train_ar": 0.31054358056520615,
        "test_ar": 0.18867752297404272,
        "train_ks": 0.24256154894828796,
        "test_ks": 0.18802914023399353,
        "learning_rate": 9.765625e-07,
        "epoch_time_seconds": 0.14551496505737305
      },
      {
        "epoch": 80,
        "train_loss": 0.5826949043707415,
        "test_loss": 0.5944938123226166,
        "train_bce_loss": 0.38886871663006867,
        "train_auc_loss": 0.6657632806084373,
        "test_bce_loss": 0.39863662123680116,
        "test_auc_loss": 0.6784326076507569,
        "train_auc": 0.6547864298192503,
        "test_auc": 0.5944064363517897,
        "train_ar": 0.30957285963850056,
        "test_ar": 0.18881287270357938,
        "train_ks": 0.24054604768753052,
        "test_ks": 0.18553146719932556,
        "learning_rate": 9.765625e-07,
        "epoch_time_seconds": 0.14780306816101074
      },
      {
        "epoch": 81,
        "train_loss": 0.5846838571808555,
        "test_loss": 0.594451081752777,
        "train_bce_loss": 0.3894383744759993,
        "train_auc_loss": 0.6683604961091821,
        "test_bce_loss": 0.3982044607400894,
        "test_auc_loss": 0.6785567700862885,
        "train_auc": 0.6548593641285914,
        "test_auc": 0.594370238168309,
        "train_ar": 0.3097187282571827,
        "test_ar": 0.18874047633661806,
        "train_ks": 0.24254536628723145,
        "test_ks": 0.18846821784973145,
        "learning_rate": 9.765625e-07,
        "epoch_time_seconds": 0.14539480209350586
      },
      {
        "epoch": 82,
        "train_loss": 0.5821575603701852,
        "test_loss": 0.5943542778491974,
        "train_bce_loss": 0.38785144686698914,
        "train_auc_loss": 0.6654316051439806,
        "test_bce_loss": 0.39745639860630033,
        "test_auc_loss": 0.6787390828132629,
        "train_auc": 0.6553406726858696,
        "test_auc": 0.5942396099409655,
        "train_ar": 0.3106813453717392,
        "test_ar": 0.18847921988193095,
        "train_ks": 0.2423989176750183,
        "test_ks": 0.19030016660690308,
        "learning_rate": 9.765625e-07,
        "epoch_time_seconds": 0.14615988731384277
      },
      {
        "epoch": 83,
        "train_loss": 0.5852278769016266,
        "test_loss": 0.5943803548812866,
        "train_bce_loss": 0.39405768432400445,
        "train_auc_loss": 0.6671579669822346,
        "test_bce_loss": 0.3974233418703079,
        "test_auc_loss": 0.6787905037403107,
        "train_auc": 0.6552309817999956,
        "test_auc": 0.5940161255038237,
        "train_ar": 0.31046196359999123,
        "test_ar": 0.1880322510076473,
        "train_ks": 0.2442517876625061,
        "test_ks": 0.19041350483894348,
        "learning_rate": 9.765625e-07,
        "epoch_time_seconds": 0.1436760425567627
      },
      {
        "epoch": 84,
        "train_loss": 0.5846425457434221,
        "test_loss": 0.5942954301834107,
        "train_bce_loss": 0.3908319947394458,
        "train_auc_loss": 0.6677042029120706,
        "test_bce_loss": 0.397190535068512,
        "test_auc_loss": 0.6787689685821533,
        "train_auc": 0.6551296841481331,
        "test_auc": 0.5940586190235619,
        "train_ar": 0.3102593682962662,
        "test_ar": 0.18811723804712388,
        "train_ks": 0.24419620633125305,
        "test_ks": 0.186447411775589,
        "learning_rate": 4.8828125e-07,
        "epoch_time_seconds": 0.14188885688781738
      },
      {
        "epoch": 85,
        "train_loss": 0.5838194652037187,
        "test_loss": 0.5942623674869537,
        "train_bce_loss": 0.39216817915439606,
        "train_auc_loss": 0.6659557358785109,
        "test_bce_loss": 0.3968636870384216,
        "test_auc_loss": 0.6788617968559265,
        "train_auc": 0.6553892955587637,
        "test_auc": 0.5940491760191755,
        "train_ar": 0.31077859111752737,
        "test_ar": 0.188098352038351,
        "train_ks": 0.2444283366203308,
        "test_ks": 0.18600833415985107,
        "learning_rate": 4.8828125e-07,
        "epoch_time_seconds": 0.14190196990966797
      },
      {
        "epoch": 86,
        "train_loss": 0.5832230096513574,
        "test_loss": 0.5942723155021667,
        "train_bce_loss": 0.39087305014783685,
        "train_auc_loss": 0.665658715096387,
        "test_bce_loss": 0.39696867763996124,
        "test_auc_loss": 0.6788310170173645,
        "train_auc": 0.6553086915700673,
        "test_auc": 0.5941231462202013,
        "train_ar": 0.31061738314013465,
        "test_ar": 0.1882462924404027,
        "train_ks": 0.24263104796409607,
        "test_ks": 0.1856825053691864,
        "learning_rate": 4.8828125e-07,
        "epoch_time_seconds": 0.13875412940979004
      },
      {
        "epoch": 87,
        "train_loss": 0.5852956988594749,
        "test_loss": 0.5943317472934723,
        "train_bce_loss": 0.39202925020998175,
        "train_auc_loss": 0.668124174529856,
        "test_bce_loss": 0.39715827703475953,
        "test_auc_loss": 0.6788346529006958,
        "train_auc": 0.6553539860915429,
        "test_auc": 0.5936934895206258,
        "train_ar": 0.3107079721830859,
        "test_ar": 0.18738697904125168,
        "train_ks": 0.2433788776397705,
        "test_ks": 0.1894974708557129,
        "learning_rate": 4.8828125e-07,
        "epoch_time_seconds": 0.14881181716918945
      },
      {
        "epoch": 88,
        "train_loss": 0.5812242410399697,
        "test_loss": 0.5943927526473999,
        "train_bce_loss": 0.3874234773895957,
        "train_auc_loss": 0.6642817096276716,
        "test_bce_loss": 0.3978542238473892,
        "test_auc_loss": 0.6786235511302948,
        "train_auc": 0.6550382268395943,
        "test_auc": 0.5941766565783904,
        "train_ar": 0.3100764536791887,
        "test_ar": 0.18835331315678072,
        "train_ks": 0.24444222450256348,
        "test_ks": 0.18858152627944946,
        "learning_rate": 4.8828125e-07,
        "epoch_time_seconds": 0.14195895195007324
      },
      {
        "epoch": 89,
        "train_loss": 0.5837072594599291,
        "test_loss": 0.5943327486515045,
        "train_bce_loss": 0.39157044752077624,
        "train_auc_loss": 0.6660516018217261,
        "test_bce_loss": 0.397467365860939,
        "test_auc_loss": 0.678703635931015,
        "train_auc": 0.6553007324688496,
        "test_auc": 0.5940727835301413,
        "train_ar": 0.31060146493769913,
        "test_ar": 0.18814556706028251,
        "train_ks": 0.2438153624534607,
        "test_ks": 0.18835487961769104,
        "learning_rate": 4.8828125e-07,
        "epoch_time_seconds": 0.14128899574279785
      },
      {
        "epoch": 90,
        "train_loss": 0.5836522606286135,
        "test_loss": 0.5944664239883423,
        "train_bce_loss": 0.3900420489636334,
        "train_auc_loss": 0.6666280762715773,
        "test_bce_loss": 0.39796148538589476,
        "test_auc_loss": 0.6786828339099884,
        "train_auc": 0.6551745445368151,
        "test_auc": 0.5939232692940253,
        "train_ar": 0.31034908907363024,
        "test_ar": 0.18784653858805056,
        "train_ks": 0.2440335750579834,
        "test_ks": 0.18787801265716553,
        "learning_rate": 2.44140625e-07,
        "epoch_time_seconds": 0.14227914810180664
      },
      {
        "epoch": 91,
        "train_loss": 0.5830812102014368,
        "test_loss": 0.594246256351471,
        "train_bce_loss": 0.39068120176141913,
        "train_auc_loss": 0.6655383489348672,
        "test_bce_loss": 0.3971577763557434,
        "test_auc_loss": 0.6787127435207367,
        "train_auc": 0.6552055126760987,
        "test_auc": 0.5942506267794161,
        "train_ar": 0.31041102535219744,
        "test_ar": 0.18850125355883218,
        "train_ks": 0.24298414587974548,
        "test_ks": 0.18509232997894287,
        "learning_rate": 2.44140625e-07,
        "epoch_time_seconds": 0.15453696250915527
      },
      {
        "epoch": 92,
        "train_loss": 0.5834878954020414,
        "test_loss": 0.5943814575672149,
        "train_bce_loss": 0.3899736174128272,
        "train_auc_loss": 0.6664225838401101,
        "test_bce_loss": 0.39743894934654234,
        "test_auc_loss": 0.67878537774086,
        "train_auc": 0.6552992853595372,
        "test_auc": 0.5937847718963599,
        "train_ar": 0.3105985707190744,
        "test_ar": 0.18756954379271984,
        "train_ks": 0.24384310841560364,
        "test_ks": 0.19140496850013733,
        "learning_rate": 2.44140625e-07,
        "epoch_time_seconds": 0.21192407608032227
      },
      {
        "epoch": 93,
        "train_loss": 0.5845028243281625,
        "test_loss": 0.5944178104400635,
        "train_bce_loss": 0.39318574287674646,
        "train_auc_loss": 0.6664958514950492,
        "test_bce_loss": 0.39789431989192964,
        "test_auc_loss": 0.6786421656608581,
        "train_auc": 0.6550984265869869,
        "test_auc": 0.5939012356171239,
        "train_ar": 0.31019685317397383,
        "test_ar": 0.18780247123424787,
        "train_ks": 0.24260324239730835,
        "test_ks": 0.1831471025943756,
        "learning_rate": 2.44140625e-07,
        "epoch_time_seconds": 0.14058923721313477
      },
      {
        "epoch": 94,
        "train_loss": 0.5871293219653043,
        "test_loss": 0.5943210542201995,
        "train_bce_loss": 0.39426316727291455,
        "train_auc_loss": 0.6697862446308136,
        "test_bce_loss": 0.3969573438167572,
        "test_auc_loss": 0.6789055109024048,
        "train_auc": 0.6551364855619008,
        "test_auc": 0.5940727835301413,
        "train_ar": 0.3102729711238017,
        "test_ar": 0.18814556706028251,
        "train_ks": 0.24177202582359314,
        "test_ks": 0.18843042850494385,
        "learning_rate": 2.44140625e-07,
        "epoch_time_seconds": 0.15168380737304688
      },
      {
        "epoch": 95,
        "train_loss": 0.58390934900804,
        "test_loss": 0.5943089306354523,
        "train_bce_loss": 0.3904227004809813,
        "train_auc_loss": 0.6668322032148187,
        "test_bce_loss": 0.3972559213638306,
        "test_auc_loss": 0.6787602305412292,
        "train_auc": 0.6550778776347519,
        "test_auc": 0.5940192731719524,
        "train_ar": 0.3101557552695038,
        "test_ar": 0.1880385463439047,
        "train_ks": 0.24177202582359314,
        "test_ks": 0.18740114569664001,
        "learning_rate": 2.44140625e-07,
        "epoch_time_seconds": 0.14475202560424805
      },
      {
        "epoch": 96,
        "train_loss": 0.5815040794285861,
        "test_loss": 0.5943914711475372,
        "train_bce_loss": 0.38883245533162897,
        "train_auc_loss": 0.6640776368704709,
        "test_bce_loss": 0.39795752465724943,
        "test_auc_loss": 0.6785774409770966,
        "train_auc": 0.6550555921513421,
        "test_auc": 0.5944111578539828,
        "train_ar": 0.31011118430268425,
        "test_ar": 0.1888223157079656,
        "train_ks": 0.24197638034820557,
        "test_ks": 0.1865985095500946,
        "learning_rate": 1.220703125e-07,
        "epoch_time_seconds": 0.14084982872009277
      },
      {
        "epoch": 97,
        "train_loss": 0.5813455744223162,
        "test_loss": 0.594379460811615,
        "train_bce_loss": 0.3875629265200008,
        "train_auc_loss": 0.664395270022479,
        "test_bce_loss": 0.3977774649858475,
        "test_auc_loss": 0.6786374568939209,
        "train_auc": 0.6550631171197663,
        "test_auc": 0.5941923949190341,
        "train_ar": 0.31012623423953256,
        "test_ar": 0.18838478983806817,
        "train_ks": 0.24110114574432373,
        "test_ks": 0.1903378963470459,
        "learning_rate": 1.220703125e-07,
        "epoch_time_seconds": 0.15468192100524902
      },
      {
        "epoch": 98,
        "train_loss": 0.5794733708555048,
        "test_loss": 0.5944178938865662,
        "train_bce_loss": 0.3851579468358647,
        "train_auc_loss": 0.6627514199777083,
        "test_bce_loss": 0.3978606522083282,
        "test_auc_loss": 0.6786567091941833,
        "train_auc": 0.6550732468849525,
        "test_auc": 0.5940003871631798,
        "train_ar": 0.310146493769905,
        "test_ar": 0.18800077432635964,
        "train_ks": 0.24073651432991028,
        "test_ks": 0.18469104170799255,
        "learning_rate": 1.220703125e-07,
        "epoch_time_seconds": 0.15657782554626465
      },
      {
        "epoch": 99,
        "train_loss": 0.5830069157210264,
        "test_loss": 0.5942701399326324,
        "train_bce_loss": 0.38967110081152484,
        "train_auc_loss": 0.6658651232719421,
        "test_bce_loss": 0.39702658653259276,
        "test_auc_loss": 0.6788030922412872,
        "train_auc": 0.6552382173465572,
        "test_auc": 0.5938854972764802,
        "train_ar": 0.31047643469311437,
        "test_ar": 0.18777099455296042,
        "train_ks": 0.2417859137058258,
        "test_ks": 0.18711313605308533,
        "learning_rate": 1.220703125e-07,
        "epoch_time_seconds": 0.1474931240081787
      },
      {
        "epoch": 100,
        "train_loss": 0.5858663672750647,
        "test_loss": 0.5943074226379395,
        "train_bce_loss": 0.39177265763282776,
        "train_auc_loss": 0.6690493740818717,
        "test_bce_loss": 0.3972490459680557,
        "test_auc_loss": 0.6787610173225402,
        "train_auc": 0.6554277886664714,
        "test_auc": 0.5941058340454932,
        "train_ar": 0.3108555773329429,
        "test_ar": 0.18821166809098644,
        "train_ks": 0.2442101538181305,
        "test_ks": 0.18883177638053894,
        "learning_rate": 1.220703125e-07,
        "epoch_time_seconds": 0.14496588706970215
      }
    ],
    "best_epoch": 11,
    "best_test_ar": 0.1980733123383871,
    "total_training_time_seconds": 15.57954216003418,
    "early_stopping_triggered": false,
    "early_stopping_epoch": null
  },
  "scorecard": {
    "segment": "CONSUMER",
    "model_type": "neural_network",
    "score_min": 0,
    "score_max": 100,
    "raw_min": "-0.22370952",
    "raw_max": "0.19678795",
    "scale_factor": "237.81355",
    "offset": "53.201157",
    "input_scale_factor": 50.0,
    "features": [
      {
        "feature_name": "monthly_income",
        "weight": -0.001524434075690806,
        "weight_normalized": -0.07622170448303223,
        "importance_rank": 1,
        "bins": [
          {
            "bin_index": 0,
            "input_value": -45,
            "bin_label": "Bin 1 (value: -45.0)",
            "raw_points": "0.06859954",
            "scaled_points": 16,
            "count_train": 550,
            "count_test": 234,
            "bad_rate_train": 0.13818182051181793,
            "bad_rate_test": 0.16239316761493683
          },
          {
            "bin_index": 1,
            "input_value": -20,
            "bin_label": "Bin 2 (value: -20.0)",
            "raw_points": "0.030488681",
            "scaled_points": 7,
            "count_train": 1114,
            "count_test": 470,
            "bad_rate_train": 0.1301615834236145,
            "bad_rate_test": 0.12765957415103912
          },
          {
            "bin_index": 2,
            "input_value": 10,
            "bin_label": "Bin 3 (value: 10.0)",
            "raw_points": "-0.0152443405",
            "scaled_points": -4,
            "count_train": 1682,
            "count_test": 690,
            "bad_rate_train": 0.1403091549873352,
            "bad_rate_test": 0.1246376782655716
          },
          {
            "bin_index": 3,
            "input_value": 35,
            "bin_label": "Bin 4 (value: 35.0)",
            "raw_points": "-0.05335519",
            "scaled_points": -13,
            "count_train": 1400,
            "count_test": 649,
            "bad_rate_train": 0.10785714536905289,
            "bad_rate_test": 0.10631740838289261
          },
          {
            "bin_index": 4,
            "input_value": 60,
            "bin_label": "Bin 5 (value: 60.0)",
            "raw_points": "-0.09146605",
            "scaled_points": -22,
            "count_train": 854,
            "count_test": 357,
            "bad_rate_train": 0.1147540956735611,
            "bad_rate_test": 0.14005602896213531
          }
        ],
        "min_points": -22,
        "max_points": 16
      },
      {
        "feature_name": "credit_utilization",
        "weight": -0.0006884915637783706,
        "weight_normalized": -0.03442457690834999,
        "importance_rank": 2,
        "bins": [
          {
            "bin_index": 0,
            "input_value": -55,
            "bin_label": "Bin 1 (value: -55.0)",
            "raw_points": "0.037867036",
            "scaled_points": 9,
            "count_train": 528,
            "count_test": 232,
            "bad_rate_train": 0.17613635957241058,
            "bad_rate_test": 0.15948276221752167
          },
          {
            "bin_index": 1,
            "input_value": -30,
            "bin_label": "Bin 2 (value: -30.0)",
            "raw_points": "0.020654747",
            "scaled_points": 5,
            "count_train": 1110,
            "count_test": 472,
            "bad_rate_train": 0.13603603839874268,
            "bad_rate_test": 0.15042373538017273
          },
          {
            "bin_index": 2,
            "input_value": 5,
            "bin_label": "Bin 3 (value: 5.0)",
            "raw_points": "-0.0034424579",
            "scaled_points": -1,
            "count_train": 1722,
            "count_test": 743,
            "bad_rate_train": 0.12659698724746704,
            "bad_rate_test": 0.12920592725276947
          },
          {
            "bin_index": 3,
            "input_value": 35,
            "bin_label": "Bin 4 (value: 35.0)",
            "raw_points": "-0.024097204",
            "scaled_points": -6,
            "count_train": 1399,
            "count_test": 582,
            "bad_rate_train": 0.10793423652648926,
            "bad_rate_test": 0.10481099784374237
          },
          {
            "bin_index": 4,
            "input_value": 65,
            "bin_label": "Bin 5 (value: 65.0)",
            "raw_points": "-0.044751953",
            "scaled_points": -11,
            "count_train": 841,
            "count_test": 371,
            "bad_rate_train": 0.11058264225721359,
            "bad_rate_test": 0.10242587327957153
          }
        ],
        "min_points": -11,
        "max_points": 9
      },
      {
        "feature_name": "recent_inquiries",
        "weight": 0.0006199434283189476,
        "weight_normalized": 0.030997171998023987,
        "importance_rank": 3,
        "bins": [
          {
            "bin_index": 0,
            "input_value": -45,
            "bin_label": "Bin 1 (value: -45.0)",
            "raw_points": "-0.027897455",
            "scaled_points": -7,
            "count_train": 1246,
            "count_test": 520,
            "bad_rate_train": 0.1492776870727539,
            "bad_rate_test": 0.1519230753183365
          },
          {
            "bin_index": 1,
            "input_value": -15,
            "bin_label": "Bin 2 (value: -15.0)",
            "raw_points": "-0.009299152",
            "scaled_points": -2,
            "count_train": 1838,
            "count_test": 785,
            "bad_rate_train": 0.11915124952793121,
            "bad_rate_test": 0.11719745397567749
          },
          {
            "bin_index": 2,
            "input_value": 15,
            "bin_label": "Bin 3 (value: 15.0)",
            "raw_points": "0.009299152",
            "scaled_points": 2,
            "count_train": 1551,
            "count_test": 673,
            "bad_rate_train": 0.11992263048887253,
            "bad_rate_test": 0.12035661190748215
          },
          {
            "bin_index": 3,
            "input_value": 45,
            "bin_label": "Bin 4 (value: 45.0)",
            "raw_points": "0.027897455",
            "scaled_points": 7,
            "count_train": 965,
            "count_test": 422,
            "bad_rate_train": 0.11917098611593246,
            "bad_rate_test": 0.12085308134555817
          }
        ],
        "min_points": -7,
        "max_points": 7
      },
      {
        "feature_name": "account_tenure",
        "weight": -0.0005854891496710479,
        "weight_normalized": -0.029274456202983856,
        "importance_rank": 4,
        "bins": [
          {
            "bin_index": 0,
            "input_value": -50,
            "bin_label": "Bin 1 (value: -50.0)",
            "raw_points": "0.029274458",
            "scaled_points": 7,
            "count_train": 554,
            "count_test": 263,
            "bad_rate_train": 0.13537906110286713,
            "bad_rate_test": 0.16349810361862183
          },
          {
            "bin_index": 1,
            "input_value": -35,
            "bin_label": "Bin 2 (value: -35.0)",
            "raw_points": "0.02049212",
            "scaled_points": 5,
            "count_train": 1128,
            "count_test": 482,
            "bad_rate_train": 0.1560283750295639,
            "bad_rate_test": 0.09336099773645401
          },
          {
            "bin_index": 2,
            "input_value": 5,
            "bin_label": "Bin 3 (value: 5.0)",
            "raw_points": "-0.0029274458",
            "scaled_points": -1,
            "count_train": 1687,
            "count_test": 700,
            "bad_rate_train": 0.125074103474617,
            "bad_rate_test": 0.1257142871618271
          },
          {
            "bin_index": 3,
            "input_value": 30,
            "bin_label": "Bin 4 (value: 30.0)",
            "raw_points": "-0.017564675",
            "scaled_points": -4,
            "count_train": 1399,
            "count_test": 599,
            "bad_rate_train": 0.1157969981431961,
            "bad_rate_test": 0.12020033597946167
          },
          {
            "bin_index": 4,
            "input_value": 55,
            "bin_label": "Bin 5 (value: 55.0)",
            "raw_points": "-0.032201905",
            "scaled_points": -8,
            "count_train": 832,
            "count_test": 356,
            "bad_rate_train": 0.09855769574642181,
            "bad_rate_test": 0.15449437499046326
          }
        ],
        "min_points": -8,
        "max_points": 7
      },
      {
        "feature_name": "payment_history",
        "weight": 0.000383820355636999,
        "weight_normalized": 0.019191017374396324,
        "importance_rank": 5,
        "bins": [
          {
            "bin_index": 0,
            "input_value": -60,
            "bin_label": "Bin 1 (value: -60.0)",
            "raw_points": "-0.023029221",
            "scaled_points": -5,
            "count_train": 589,
            "count_test": 260,
            "bad_rate_train": 0.2122241109609604,
            "bad_rate_test": 0.20000000298023224
          },
          {
            "bin_index": 1,
            "input_value": -25,
            "bin_label": "Bin 2 (value: -25.0)",
            "raw_points": "-0.009595509",
            "scaled_points": -2,
            "count_train": 1100,
            "count_test": 473,
            "bad_rate_train": 0.16909091174602509,
            "bad_rate_test": 0.17336152493953705
          },
          {
            "bin_index": 2,
            "input_value": 10,
            "bin_label": "Bin 3 (value: 10.0)",
            "raw_points": "0.0038382036",
            "scaled_points": 1,
            "count_train": 1664,
            "count_test": 719,
            "bad_rate_train": 0.109375,
            "bad_rate_test": 0.11682892590761185
          },
          {
            "bin_index": 3,
            "input_value": 40,
            "bin_label": "Bin 4 (value: 40.0)",
            "raw_points": "0.015352814",
            "scaled_points": 4,
            "count_train": 1434,
            "count_test": 589,
            "bad_rate_train": 0.09972105920314789,
            "bad_rate_test": 0.10356536507606506
          },
          {
            "bin_index": 4,
            "input_value": 75,
            "bin_label": "Bin 5 (value: 75.0)",
            "raw_points": "0.028786527",
            "scaled_points": 7,
            "count_train": 813,
            "count_test": 359,
            "bad_rate_train": 0.08610086143016815,
            "bad_rate_test": 0.06685236841440201
          }
        ],
        "min_points": -5,
        "max_points": 7
      },
      {
        "feature_name": "num_credit_lines",
        "weight": -0.00010907340765697882,
        "weight_normalized": -0.005453670397400856,
        "importance_rank": 6,
        "bins": [
          {
            "bin_index": 0,
            "input_value": -40,
            "bin_label": "Bin 1 (value: -40.0)",
            "raw_points": "0.004362936",
            "scaled_points": 1,
            "count_train": 1244,
            "count_test": 497,
            "bad_rate_train": 0.13987138867378235,
            "bad_rate_test": 0.12474849075078964
          },
          {
            "bin_index": 1,
            "input_value": -10,
            "bin_label": "Bin 2 (value: -10.0)",
            "raw_points": "0.001090734",
            "scaled_points": 0,
            "count_train": 1938,
            "count_test": 800,
            "bad_rate_train": 0.12125902622938156,
            "bad_rate_test": 0.1274999976158142
          },
          {
            "bin_index": 2,
            "input_value": 20,
            "bin_label": "Bin 3 (value: 20.0)",
            "raw_points": "-0.002181468",
            "scaled_points": -1,
            "count_train": 1537,
            "count_test": 681,
            "bad_rate_train": 0.1242680549621582,
            "bad_rate_test": 0.12187959253787994
          },
          {
            "bin_index": 3,
            "input_value": 40,
            "bin_label": "Bin 4 (value: 40.0)",
            "raw_points": "-0.004362936",
            "scaled_points": -1,
            "count_train": 881,
            "count_test": 422,
            "bad_rate_train": 0.12031782418489456,
            "bad_rate_test": 0.13270142674446106
          }
        ],
        "min_points": -1,
        "max_points": 1
      }
    ],
    "min_possible_score": 0,
    "max_possible_score": 100
  }
}